easyesn/BaseESN.py
easyesn/ClassificationESN.py
easyesn/FeatureGeneratorESN.py
easyesn/OneHotEncoder.py
easyesn/PredictionESN.py
easyesn/RegressionESN.py
easyesn/SpatioTemporalESN.py
easyesn/__init__.py
easyesn/__version__.py
easyesn/helper.py
easyesn/backend/__init__.py
easyesn/backend/cupyBackend.py
easyesn/backend/numpyBackend.py
easyesn/backend/torchBackend.py
easyesn/optimizers/GradientOptimizer.py
easyesn/optimizers/GridSearchOptimizer.py
easyesn/optimizers/Pipeline.py
easyesn/optimizers/__init__.py
easyesn-0.1.6.1.dist-info/METADATA
easyesn-0.1.6.1.dist-info/WHEEL
easyesn-0.1.6.1.dist-info/top_level.txt
easyesn-0.1.6.1.dist-info/RECORD
