Metadata-Version: 2.1
Name: easyesn
Version: 0.1.6.1
Summary: Python library for Reservoir Computing using Echo State Networks
Home-page: https://github.com/kalekiu/easyesn
Author: Roland Zimmermann, Luca Thiede
Author-email: rzrolandzimmermann@gmail.com
License: MIT
Platform: UNKNOWN
Classifier: License :: OSI Approved :: MIT License
Classifier: Programming Language :: Python
Classifier: Programming Language :: Python :: 3
Classifier: Programming Language :: Python :: 3.6
Classifier: Programming Language :: Python :: Implementation :: CPython
Classifier: Programming Language :: Python :: Implementation :: PyPy
Classifier: Intended Audience :: Science/Research
Classifier: Intended Audience :: Developers
Classifier: Topic :: Scientific/Engineering
Classifier: Topic :: Scientific/Engineering :: Artificial Intelligence
Requires-Python: >=3.6.0
Requires-Dist: numpy
Requires-Dist: progressbar2
Requires-Dist: dill
Requires-Dist: multiprocess
Requires-Dist: sklearn
